illuminator/__init__.py
illuminator/engine.py
illuminator/builder/__init__.py
illuminator/builder/model.py
illuminator/builder/mosaik_tutorial.py
illuminator/builder/validate_yaml.py
illuminator/cli/__init__.py
illuminator/cli/main.py
illuminator/cli/state_space_simulator.py
illuminator/cli/yaml_interpreter.py
illuminator/cluster/__init__.py
illuminator/cluster/build_runshfile.py
illuminator/models/CSV_reader_v3.py
illuminator/models/__init__.py
illuminator/models/adder.py
illuminator/models/collector.py
illuminator/models/construct_model.py
illuminator/models/influxdbwriter.py
illuminator/models/model_template.py
illuminator/models/mosaik_csv.py
illuminator/models/mosaik_sql.py
illuminator/models/mqttsend.py
illuminator/models/submqtt.py
illuminator/models/test_model.py
illuminator/models/Agents/generators/generation_company_agent.py
illuminator/models/Agents/generators/generation_company_agent_mosaik.py
illuminator/models/Agents/generators/generation_company_agent_v3.py
illuminator/models/Agents/justice_agent/JusticeScoreAgent_class_IDE.py
illuminator/models/Agents/justice_agent/justice_agent_v3.py
illuminator/models/Agents/operators/operator.py
illuminator/models/Agents/operators/operator_mosaik.py
illuminator/models/Agents/operators/operator_v3.py
illuminator/models/Agents/prosumers/prosumer_S_model.py
illuminator/models/Agents/prosumers/prosumer_model.py
illuminator/models/Agents/prosumers/prosumer_mosaik.py
illuminator/models/Battery/__init__.py
illuminator/models/Battery/battery_model.py
illuminator/models/Battery/battery_v3.py
illuminator/models/Controllers/__init__.py
illuminator/models/Controllers/controller_T1/controller_T1_model.py
illuminator/models/Controllers/controller_T1/controller_T1_mosaik.py
illuminator/models/Controllers/controller_T1/controller_T1_v3.py
illuminator/models/Controllers/controller_T3Congestion/controller_T3Congestion_model.py
illuminator/models/Controllers/controller_T3Congestion/controller_T3Congestion_mosaik.py
illuminator-3.0.0b7.dist-info/METADATA
illuminator-3.0.0b7.dist-info/WHEEL
illuminator-3.0.0b7.dist-info/entry_points.txt
illuminator-3.0.0b7.dist-info/licenses/LICENSE
illuminator-3.0.0b7.dist-info/RECORD
