Metadata-Version: 2.4
Name: illuminator
Version: 3.0.0b7
Summary: A development toolkit for simulating energy systems
Project-URL: Documentation, https://illuminator-team.github.io/Illuminator/
Project-URL: Repository, https://github.com/Illuminator-team/Illuminator.git
Project-URL: Bug Tracker, https://github.com/Illuminator-team/Illuminator/issues
Project-URL: Changelog, https://github.com/Illuminator-team/Illuminator/blob/main/CHANGELOG.md
Author: Jort Groen, Despoina Georgiadi, Josip Grguric, Joan Pijpker, Manuel Garcia Alvarez, Mano Rom
Maintainer-email: Illuminator Team <illuminator@tudelft.nl>
License:                   GNU LESSER GENERAL PUBLIC LICENSE
License-File: LICENSE
Keywords: development,energy,simulation,toolkit
Classifier: Development Status :: 5 - Production/Stable
Classifier: Programming Language :: Python
Requires-Python: >=3.8
Requires-Dist: arrow==1.2.3
Requires-Dist: lxml==4.9.3
Requires-Dist: matplotlib==3.7.2
Requires-Dist: mosaik>=3.3.3
Requires-Dist: numpy==1.26.4
Requires-Dist: paho-mqtt==1.6.1
Requires-Dist: pandapower==2.13.1
Requires-Dist: pandas==1.5.3
Requires-Dist: ruamel-yaml>=0.18.5
Requires-Dist: schema>=0.7.7
Requires-Dist: typer>=0.12.5
Provides-Extra: dev
Requires-Dist: myst-parser; extra == 'dev'
Requires-Dist: nbsphinx; extra == 'dev'
Requires-Dist: pytest; extra == 'dev'
Requires-Dist: sphinx; extra == 'dev'
Requires-Dist: sphinx-copybutton; extra == 'dev'
Requires-Dist: sphinx-rtd-theme; extra == 'dev'
